{
  "metadata" : {
    "id" : "af765f08-72b2-4c45-b23d-8c841ae5f739",
    "name" : "churn",
    "modified_at" : "2022-02-16T05:35:31.178Z",
    "created_at" : "2022-02-16T05:35:31.178Z",
    "owner" : "IBMid-270004NNP7",
    "space_id" : "c02ba4d1-e91e-4028-a985-1ebcf2e9790c"
  },
  "entity" : {
    "name" : "churn",
    "space_id" : "c02ba4d1-e91e-4028-a985-1ebcf2e9790c",
    "custom" : { },
    "online" : { },
    "status" : {
      "state" : "ready",
      "online_url" : {
        "url" : "https://us-south.ml.cloud.ibm.com/ml/v4/deployments/af765f08-72b2-4c45-b23d-8c841ae5f739/predictions"
      }
    },
    "asset" : {
      "id" : "352018bf-5d46-4a44-bd0a-9a9b5908b3ae"
    }
  },
  "name" : "churn",
  "status" : "ready",
  "deployedAt" : "2022-02-16T05:35:31.178Z"
}